configs/__init__.py
configs/configs_base.py
configs/configs_data.py
configs/configs_inference.py
configs/configs_model_type.py
protenix/__init__.py
protenix/config/__init__.py
protenix/config/config.py
protenix/config/extend_types.py
protenix/data/__init__.py
protenix/data/ccd.py
protenix/data/compute_esm.py
protenix/data/constants.py
protenix/data/constraint_featurizer.py
protenix/data/data_pipeline.py
protenix/data/dataloader.py
protenix/data/dataset.py
protenix/data/esm_featurizer.py
protenix/data/featurizer.py
protenix/data/filter.py
protenix/data/infer_data_pipeline.py
protenix/data/json_maker.py
protenix/data/json_parser.py
protenix/data/json_to_feature.py
protenix/data/msa_featurizer.py
protenix/data/msa_utils.py
protenix/data/parser.py
protenix/data/substructure_perms.py
protenix/data/tokenizer.py
protenix/data/utils.py
protenix/metrics/__init__.py
protenix/metrics/clash.py
protenix/metrics/lddt_metrics.py
protenix/metrics/rmsd.py
protenix/model/__init__.py
protenix/model/generator.py
protenix/model/loss.py
protenix/model/protenix.py
protenix/model/sample_confidence.py
protenix/model/utils.py
protenix/model/layer_norm/__init__.py
protenix/model/layer_norm/layer_norm.py
protenix/model/layer_norm/torch_ext_compile.py
protenix/model/layer_norm/kernel/compat.h
protenix/model/layer_norm/kernel/layer_norm_cuda.cpp
protenix/model/layer_norm/kernel/layer_norm_cuda_kernel.cu
protenix/model/layer_norm/kernel/type_shim.h
protenix/model/modules/__init__.py
protenix/model/modules/confidence.py
protenix/model/modules/diffusion.py
protenix/model/modules/embedders.py
protenix/model/modules/frames.py
protenix/model/modules/head.py
protenix/model/modules/pairformer.py
protenix/model/modules/primitives.py
protenix/model/modules/transformer.py
protenix/model/tri_attention/__init__.py
protenix/model/tri_attention/autotune.py
protenix/model/tri_attention/autotune_helpers.py
protenix/model/tri_attention/backward.py
protenix/model/tri_attention/forward.py
protenix-0.7.1.dist-info/licenses/LICENSE
protenix-0.7.1.dist-info/METADATA
protenix-0.7.1.dist-info/WHEEL
protenix-0.7.1.dist-info/entry_points.txt
protenix-0.7.1.dist-info/top_level.txt
protenix-0.7.1.dist-info/RECORD
