Metadata-Version: 2.4
Name: protenix
Version: 0.7.1
Summary: A trainable PyTorch reproduction of AlphaFold 3.
Home-page: https://github.com/bytedance/Protenix
Author: Bytedance Inc.
Author-email: ai4s-bio@bytedance.com
License: Apache 2.0 License
Platform: manylinux1
Requires-Python: >=3.11
License-File: LICENSE
Requires-Dist: torch==2.7.1
Requires-Dist: torchvision==0.22.1
Requires-Dist: torchaudio==2.7.1
Requires-Dist: cuequivariance-ops-torch-cu12==0.6.1
Requires-Dist: cuequivariance-torch==0.6.1
Requires-Dist: scipy>=1.9.0
Requires-Dist: ml_collections==1.1.0
Requires-Dist: tqdm==4.67.1
Requires-Dist: pandas==2.3.1
Requires-Dist: dm-tree==0.1.9
Requires-Dist: PyYAML==6.0.2
Requires-Dist: matplotlib==3.10.5
Requires-Dist: ipywidgets==8.1.7
Requires-Dist: py3Dmol==2.5.2
Requires-Dist: rdkit==2023.9.6
Requires-Dist: biopython==1.85
Requires-Dist: biotite==1.4.0
Requires-Dist: modelcif==1.4
Requires-Dist: gemmi==0.6.7
Requires-Dist: pdbeccdutils==0.8.6
Requires-Dist: fair-esm==2.0.0
Requires-Dist: scikit-learn==1.7.1
Requires-Dist: scikit-learn-extra==0.3.0
Requires-Dist: deepspeed==0.17.5
Requires-Dist: pydantic>=2.0.0
Requires-Dist: triton==3.3.1
Requires-Dist: optree==0.17.0
Requires-Dist: protobuf==6.31.1
Requires-Dist: icecream==2.1.7
Requires-Dist: ipdb==0.13.13
Requires-Dist: wandb==0.21.1
Requires-Dist: posix_ipc==1.3.0
Requires-Dist: numpy==1.26.4
Dynamic: author
Dynamic: author-email
Dynamic: description
Dynamic: description-content-type
Dynamic: home-page
Dynamic: license
Dynamic: license-file
Dynamic: platform
Dynamic: requires-dist
Dynamic: requires-python
Dynamic: summary
